rxnmapper/__init__.py
rxnmapper/attention.py
rxnmapper/batched_mapper.py
rxnmapper/core.py
rxnmapper/py.typed
rxnmapper/smiles_utils.py
rxnmapper/tokenization_smiles.py
rxnmapper/models/transformers/albert_heads_8_uspto_all_1310k/config.json
rxnmapper/models/transformers/albert_heads_8_uspto_all_1310k/pytorch_model.bin
rxnmapper/models/transformers/albert_heads_8_uspto_all_1310k/special_tokens_map.json
rxnmapper/models/transformers/albert_heads_8_uspto_all_1310k/tokenizer_config.json
rxnmapper/models/transformers/albert_heads_8_uspto_all_1310k/training_args.bin
rxnmapper/models/transformers/albert_heads_8_uspto_all_1310k/vocab.txt
rxnmapper-0.4.2.dist-info/licenses/LICENSE
tests/__init__.py
tests/test_batched_mapper.py
tests/test_mapper.py
tests/test_smiles_utils.py
tests/utils.py
rxnmapper-0.4.2.dist-info/METADATA
rxnmapper-0.4.2.dist-info/WHEEL
rxnmapper-0.4.2.dist-info/top_level.txt
rxnmapper-0.4.2.dist-info/RECORD
