Metadata-Version: 2.4
Name: rxnmapper
Version: 0.4.2
Summary: Reaction atom-mapping from transformers
Home-page: https://github.com/rxn4chemistry/rxnmapper
Author: IBM RXN team
Author-email: rxn4chemistry@zurich.ibm.com
License: MIT
Classifier: Operating System :: OS Independent
Classifier: Intended Audience :: Developers
Classifier: Intended Audience :: Science/Research
Classifier: License :: OSI Approved :: MIT License
Classifier: Programming Language :: Python :: 3
Classifier: Programming Language :: Python :: 3.6
Classifier: Programming Language :: Python :: 3.7
Classifier: Programming Language :: Python :: 3.8
Classifier: Programming Language :: Python :: 3.9
Classifier: Programming Language :: Python :: 3.10
Classifier: Programming Language :: Python :: 3.11
Classifier: Topic :: Software Development :: Libraries :: Python Modules
Requires-Python: >=3.6
License-File: LICENSE
Requires-Dist: pandas>=1.0.3
Requires-Dist: rxn-chem-utils>=1.0.3
Requires-Dist: scipy>=1.4.1
Requires-Dist: torch>=1.5.0
Requires-Dist: transformers>=4.0.0
Provides-Extra: dev
Requires-Dist: black>=22.1.0; extra == "dev"
Requires-Dist: bump2version>=1.0.1; extra == "dev"
Requires-Dist: flake8>=3.7.9; extra == "dev"
Requires-Dist: isort>=5.10.0; extra == "dev"
Requires-Dist: mypy>=0.910; extra == "dev"
Requires-Dist: pytest>=5.4.1; extra == "dev"
Requires-Dist: sphinx-rtd-theme==0.4.3; extra == "dev"
Requires-Dist: sphinx==2.2.1; extra == "dev"
Requires-Dist: twine==3.1.1; extra == "dev"
Requires-Dist: types-setuptools>=62.6.0; extra == "dev"
Provides-Extra: rdkit
Requires-Dist: rdkit-pypi>=2021.3.2; python_version < "3.7" and extra == "rdkit"
Requires-Dist: rdkit>=2022.3.4; python_version >= "3.7" and extra == "rdkit"
Dynamic: license-file
